{
    "news": [
        {
            "title": "13 000 youths set to benefit from Youth Employment and Entrepreneurship Project",
            "href": "https://www.zbcnews.co.zw/13-000-youths-set-to-benefit-from-youth-employment-and-entrepreneurship-project/",
            "img_url": "https://www.zbcnews.co.zw/wp-content/uploads/2025/07/WhatsApp-Image-2025-07-16-at-4.12.19-PM.jpeg",
            "category": "Business",
            "time": "21:31",
            "date": "16 Jul 2025"
        },
        {
            "title": "State of sugar industry value chain under the spotlight",
            "href": "https://www.zbcnews.co.zw/state-of-sugar-industry-value-chain-under-the-spotlight/",
            "img_url": "https://www.zbcnews.co.zw/wp-content/uploads/2025/07/IMG-20250715-WA0076.jpg",
            "category": "Business",
            "time": "21:31",
            "date": "16 Jul 2025"
        },
        {
            "title": "China-Zimbabwe trade grows by 18 percent as investment relations strengthen",
            "href": "https://www.zbcnews.co.zw/china-zimbabwe-trade-grows-by-18-percent-as-investment-relations-strengthen/",
            "img_url": "https://www.zbcnews.co.zw/wp-content/uploads/2025/07/WhatsApp-Image-2025-07-15-at-1.42.02-PM-1.jpeg",
            "category": "Business",
            "time": "21:31",
            "date": "16 Jul 2025"
        },
        {
            "title": "Cross-border traders in Matabeleland North benefit from Presidential revolving fund",
            "href": "https://www.zbcnews.co.zw/cross-border-traders-in-matabeleland-north-benefit-from-presidential-revolving-fund/",
            "img_url": "https://www.zbcnews.co.zw/wp-content/uploads/2025/07/WhatsApp-Image-2025-07-13-at-5.33.52-PM-1.jpeg",
            "category": "Business",
            "time": "21:31",
            "date": "16 Jul 2025"
        },
        {
            "title": "Mat North Investment Indaba pushes for private sector-led growth",
            "href": "https://www.zbcnews.co.zw/mat-north-investment-indaba-pushes-for-private-sector-led-growth/",
            "img_url": "https://www.zbcnews.co.zw/wp-content/uploads/2025/07/WhatsApp-Image-2025-07-12-at-2.47.11-PM.jpeg",
            "category": "Business",
            "time": "21:31",
            "date": "16 Jul 2025"
        },
        {
            "title": "Small-scale miners gear up for digital transformation through landmark deal",
            "href": "https://www.zbcnews.co.zw/small-scale-miners-gear-up-for-digital-transformation-through-landmark-deal/",
            "img_url": "https://www.zbcnews.co.zw/wp-content/uploads/2025/07/WhatsApp-Image-2025-07-11-at-14.05.42.jpeg",
            "category": "Business",
            "time": "21:31",
            "date": "16 Jul 2025"
        },
        {
            "title": "Business extravaganza in Matabeleland North attracts investors",
            "href": "https://www.zbcnews.co.zw/business-extravaganza-in-matabeleland-north-attracts-investors/",
            "img_url": "https://www.zbcnews.co.zw/wp-content/uploads/2025/07/WhatsApp-Image-2025-07-11-at-15.10.05.jpeg",
            "category": "Business",
            "time": "21:31",
            "date": "16 Jul 2025"
        },
        {
            "title": "UAE becomes one of top ten global trade partners for Eurasian Economic Union",
            "href": "https://www.zbcnews.co.zw/uae-becomes-one-of-top-ten-global-trade-partners-for-eurasian-economic-union/",
            "img_url": "https://www.zbcnews.co.zw/wp-content/uploads/2025/07/ktuy489d2qu25tpttzq0d5w9acqm5pfq.jpg",
            "category": "Business",
            "time": "21:31",
            "date": "16 Jul 2025"
        },
        {
            "title": "Zimbabwe on track to halt cement imports as new plants take shape",
            "href": "https://www.zbcnews.co.zw/zimbabwe-on-track-to-halt-cement-imports-as-new-plants-take-shape/",
            "img_url": "https://www.zbcnews.co.zw/wp-content/uploads/2025/07/d77bb2e8-6270-4c6c-980d-fbace8229850.jpeg",
            "category": "Business",
            "time": "21:31",
            "date": "16 Jul 2025"
        },
        {
            "title": "RBZ Quarterly Report Shows Signs of Economic Stability",
            "href": "https://www.zbcnews.co.zw/rbz-quarterly-report-shows-signs-of-economic-stability/",
            "img_url": "https://www.zbcnews.co.zw/wp-content/uploads/2025/07/WhatsApp-Image-2025-07-09-at-11.51.38-AM-1.jpeg",
            "category": "Business",
            "time": "21:31",
            "date": "16 Jul 2025"
        },
        {
            "title": "Zimbabwe set to resume wheat exports",
            "href": "https://www.zbcnews.co.zw/zimbabwe-set-to-resume-wheat-exports/",
            "img_url": "https://www.zbcnews.co.zw/wp-content/uploads/2025/07/WhatsApp-Image-2025-07-08-at-5.31.44-PM.jpeg",
            "category": "Business",
            "time": "21:31",
            "date": "16 Jul 2025"
        },
        {
            "title": "Local firms scale up exports to Zambia",
            "href": "https://www.zbcnews.co.zw/local-firms-scale-up-exports-to-zambia/",
            "img_url": "https://www.zbcnews.co.zw/wp-content/uploads/2025/07/zim-zambia.jpg",
            "category": "Business",
            "time": "21:31",
            "date": "16 Jul 2025"
        }
    ]
}