{
    "news": [
        {
            "title": "2025 legal year to be opened in Bulawayo",
            "href": "https://www.zbcnews.co.zw/2025-legal-year-to-be-opened-in-bulawayo/",
            "img_url": "https://www.zbcnews.co.zw/wp-content/uploads/2025/01/Chief-Justice-Luke-Malaba-324x380.jpg",
            "category": "Local News",
            "time": "08:34",
            "date": "14 Jan 2025"
        },
        {
            "title": "Govt intensifies efforts to end HIV/AIDS in children",
            "href": "https://www.zbcnews.co.zw/govt-intensifies-efforts-to-end-hiv-aids-in-children/",
            "img_url": "https://www.zbcnews.co.zw/wp-content/uploads/2025/01/98498643-48-sa-slashes-new-hiv-cases-by-almost-half-324x400.jpeg",
            "category": "Local News",
            "time": "08:34",
            "date": "14 Jan 2025"
        },
        {
            "title": "Food distribution programme to continue",
            "href": "https://www.zbcnews.co.zw/food-distribution-programme-to-continue/",
            "img_url": "https://www.zbcnews.co.zw/wp-content/uploads/2025/01/food-distribution-324x240.jpg",
            "category": "Local News",
            "time": "08:34",
            "date": "14 Jan 2025"
        },
        {
            "title": "Bindura hailstorm leaves 14 families homeless",
            "href": "https://www.zbcnews.co.zw/bindura-hailstorm-leaves-14-families-homeless/",
            "img_url": "https://www.zbcnews.co.zw/wp-content/uploads/2025/01/Pqp1IBmUYhazjSoAqG0Wvn1BXHZqpeo6eYWp0Mwt-324x400.jpg",
            "category": "Local News",
            "time": "08:34",
            "date": "14 Jan 2025"
        },
        {
            "title": "2024 A Level results out",
            "href": "https://www.zbcnews.co.zw/2024-a-level-results-out/",
            "img_url": "https://www.zbcnews.co.zw/wp-content/uploads/2025/01/Zimsec-Logo-pcpmuri0zlq7yowmhh6yw1oe0uw64vm8oh4v6encla.jpg",
            "category": "Local News",
            "time": "08:34",
            "date": "14 Jan 2025"
        },
        {
            "title": "Manicaland province increases milk output",
            "href": "https://www.zbcnews.co.zw/manicaland-province-increases-milk-output/",
            "img_url": "https://www.zbcnews.co.zw/wp-content/uploads/2025/01/milk-324x380.jpg",
            "category": "Local News",
            "time": "08:34",
            "date": "14 Jan 2025"
        },
        {
            "title": "Harare City Council in strategic partnership for water treatment & billing",
            "href": "https://www.zbcnews.co.zw/harare-city-council-in-strategic-partnership-for-water-treatment-billing/",
            "img_url": "https://www.zbcnews.co.zw/wp-content/uploads/2025/01/download-1.jpg",
            "category": "Local News",
            "time": "08:34",
            "date": "14 Jan 2025"
        },
        {
            "title": "Bulawayo residents fed up with sewage pipe bursts",
            "href": "https://www.zbcnews.co.zw/bulawayo-residents-fed-up-with-sewage-pipe-bursts/",
            "img_url": "https://www.zbcnews.co.zw/wp-content/uploads/2025/01/sewage-696x392.jpg",
            "category": "Local News",
            "time": "08:34",
            "date": "14 Jan 2025"
        },
        {
            "title": "Current rains push dam levels up",
            "href": "https://www.zbcnews.co.zw/current-rains-pushes-dam-levels-up/",
            "img_url": "https://www.zbcnews.co.zw/wp-content/uploads/2025/01/dam-levels-1.jpg",
            "category": "Local News",
            "time": "08:34",
            "date": "14 Jan 2025"
        },
        {
            "title": "Revitalisation of NRZ on course",
            "href": "https://www.zbcnews.co.zw/revitalisation-of-nrz-on-course/",
            "img_url": "https://www.zbcnews.co.zw/wp-content/uploads/2025/01/NRZ.jpg",
            "category": "Local News",
            "time": "08:34",
            "date": "14 Jan 2025"
        },
        {
            "title": "Government commissions fire tenders for Redcliff municipality",
            "href": "https://www.zbcnews.co.zw/government-commissions-fire-tenders-for-redcliff-municipality/",
            "img_url": "https://www.zbcnews.co.zw/wp-content/uploads/2025/01/IMG-20250108-WA0072-696x477.jpg",
            "category": "Local News",
            "time": "08:34",
            "date": "14 Jan 2025"
        }
    ]
}