{
    "news": [
        {
            "title": "Vic Falls urged to leverage tourism heritage for sports and cultural growth",
            "href": "https://www.zbcnews.co.zw/vic-falls-urged-to-leverage-tourism-heritage-for-sports-and-cultural-growth/",
            "img_url": "https://www.zbcnews.co.zw/wp-content/uploads/2025/03/WhatsApp-Image-2025-03-27-at-12.41.48-324x400.jpeg",
            "category": "Sport",
            "time": "21:46",
            "date": "28 Mar 2025"
        },
        {
            "title": "Parliament Committee assesses sports facilities across the country",
            "href": "https://www.zbcnews.co.zw/parliament-committee-assesses-sports-facilities-across-the-country/",
            "img_url": "https://www.zbcnews.co.zw/wp-content/uploads/2025/03/WhatsApp-Image-2025-03-26-at-2.48.19-PM-324x400.jpeg",
            "category": "Sport",
            "time": "21:46",
            "date": "28 Mar 2025"
        },
        {
            "title": "Lieutenant General (Rtd) Anselem Sanyatwe, takes over as Minister of Sport, Recreation, Arts, and Culture",
            "href": "https://www.zbcnews.co.zw/lieutenant-general-rtd-anselem-sanyatwe-takes-over-as-minister-of-sport-recreation-arts-and-culture/",
            "img_url": "https://www.zbcnews.co.zw/wp-content/uploads/2025/03/WhatsApp-Image-2025-03-25-at-8.03.06-PM-324x400.jpeg",
            "category": "Sport",
            "time": "21:46",
            "date": "28 Mar 2025"
        },
        {
            "title": "Pool action heads to Binga as ZIPA unveils Gazaman Tournament",
            "href": "https://www.zbcnews.co.zw/pool-action-heads-to-binga-as-zipa-unveils-gazaman-tournament/",
            "img_url": "https://www.zbcnews.co.zw/wp-content/uploads/2025/03/pool1-324x400.jpg",
            "category": "Sport",
            "time": "21:46",
            "date": "28 Mar 2025"
        },
        {
            "title": "Harare Gears Up for the 4th Edition of the Nedbank Rugby Challenge Cup",
            "href": "https://www.zbcnews.co.zw/harare-gears-up-for-the-4th-edition-of-the-nedbank-rugby-challenge-cup/",
            "img_url": "https://www.zbcnews.co.zw/wp-content/uploads/2025/03/rugby-324x400.jpg",
            "category": "Sport",
            "time": "21:46",
            "date": "28 Mar 2025"
        },
        {
            "title": "Falcon, ZDF Queens dominate as PNL season kicks off",
            "href": "https://www.zbcnews.co.zw/falcon-zdf-queens-dominate-as-pnl-season-kicks-off/",
            "img_url": "https://www.zbcnews.co.zw/wp-content/uploads/2025/03/netball-3-696x522.jpg",
            "category": "Sport",
            "time": "21:46",
            "date": "28 Mar 2025"
        },
        {
            "title": "Zim Saints eye topflight return",
            "href": "https://www.zbcnews.co.zw/zim-saints-eye-topflight-return/",
            "img_url": "https://www.zbcnews.co.zw/wp-content/uploads/2025/03/ruzive-696x870.jpg",
            "category": "Sport",
            "time": "21:46",
            "date": "28 Mar 2025"
        },
        {
            "title": "Zim Footgolf Association trains officials to expand new sport nationwide",
            "href": "https://www.zbcnews.co.zw/zim-footgolf-association-trains-officials-to-expand-new-sport-nationwide/",
            "img_url": "https://www.zbcnews.co.zw/wp-content/uploads/2025/03/footgolf-696x522.jpg",
            "category": "Sport",
            "time": "21:46",
            "date": "28 Mar 2025"
        },
        {
            "title": "Warriors touch down in Lagos ahead of Nigeria clash",
            "href": "https://www.zbcnews.co.zw/warriors-touch-down-in-lagos-ahead-of-nigeria-clash/",
            "img_url": "https://www.zbcnews.co.zw/wp-content/uploads/2025/03/bhora-696x522.jpg",
            "category": "Sport",
            "time": "21:46",
            "date": "28 Mar 2025"
        },
        {
            "title": "NAAZ targets improved performance at Region Five youth games",
            "href": "https://www.zbcnews.co.zw/naaz-targets-improved-performance-at-region-five-youth-games/",
            "img_url": "https://www.zbcnews.co.zw/wp-content/uploads/2025/03/NAAZ-2-696x522.jpg",
            "category": "Sport",
            "time": "21:46",
            "date": "28 Mar 2025"
        },
        {
            "title": "Warriors set sights on Nigeria after Benin stalemate",
            "href": "https://www.zbcnews.co.zw/warriors-set-sights-on-nigeria-after-benin-stalemate/",
            "img_url": "https://www.zbcnews.co.zw/wp-content/uploads/2025/03/WhatsApp-Image-2025-03-21-at-2.25.22-PM-1-696x435.jpeg",
            "category": "Sport",
            "time": "21:46",
            "date": "28 Mar 2025"
        },
        {
            "title": "Manicaland and Harare dominate at NAPH games",
            "href": "https://www.zbcnews.co.zw/manicaland-and-harare-dominate-at-naph-games/",
            "img_url": "https://www.zbcnews.co.zw/wp-content/uploads/2025/03/naph-696x522.jpg",
            "category": "Sport",
            "time": "21:46",
            "date": "28 Mar 2025"
        }
    ]
}